odoo/addons/account_check_printing_report_sslm102/README.rst
odoo/addons/account_check_printing_report_sslm102/__init__.py
odoo/addons/account_check_printing_report_sslm102/__manifest__.py
odoo/addons/account_check_printing_report_sslm102/data/report_paperformat.xml
odoo/addons/account_check_printing_report_sslm102/data/report_paperformat_parameter.xml
odoo/addons/account_check_printing_report_sslm102/i18n/account_check_printing_report_sslm102.pot
odoo/addons/account_check_printing_report_sslm102/i18n/es.po
odoo/addons/account_check_printing_report_sslm102/i18n/pt.po
odoo/addons/account_check_printing_report_sslm102/models/__init__.py
odoo/addons/account_check_printing_report_sslm102/models/account_journal.py
odoo/addons/account_check_printing_report_sslm102/models/res_company.py
odoo/addons/account_check_printing_report_sslm102/readme/CONFIGURE.rst
odoo/addons/account_check_printing_report_sslm102/readme/CONTRIBUTORS.rst
odoo/addons/account_check_printing_report_sslm102/readme/DESCRIPTION.rst
odoo/addons/account_check_printing_report_sslm102/readme/INSTALL.rst
odoo/addons/account_check_printing_report_sslm102/readme/USAGE.rst
odoo/addons/account_check_printing_report_sslm102/report/__init__.py
odoo/addons/account_check_printing_report_sslm102/report/account_check_writing_report.xml
odoo/addons/account_check_printing_report_sslm102/report/check_print.py
odoo/addons/account_check_printing_report_sslm102/static/description/icon.png
odoo/addons/account_check_printing_report_sslm102/static/description/index.html
odoo/addons/account_check_printing_report_sslm102/views/report_check.xml
odoo14_addon_account_check_printing_report_sslm102-14.0.1.0.1.dist-info/METADATA
odoo14_addon_account_check_printing_report_sslm102-14.0.1.0.1.dist-info/WHEEL
odoo14_addon_account_check_printing_report_sslm102-14.0.1.0.1.dist-info/top_level.txt
odoo14_addon_account_check_printing_report_sslm102-14.0.1.0.1.dist-info/RECORD
